nts/service/__helpers.py
nts/service/__init__.py
nts/service/redis_service.py
nts/service/simple_service.py
nts.service-0.0.1.dist-info/LICENSE
nts.service-0.0.1.dist-info/METADATA
nts.service-0.0.1.dist-info/WHEEL
nts.service-0.0.1.dist-info/top_level.txt
nts.service-0.0.1.dist-info/RECORD
