Metadata-Version: 2.1
Name: nts.service
Version: 0.0.1
Summary: Simple service daemon impementation
Author-email: Anton Bondarenko <bond.anton@gmail.com>
License: MIT License
Project-URL: Homepage, https://github.com/bond-anton/nts.service
Project-URL: Bug Tracker, https://github.com/bond-anton/nts.service/issues
Classifier: Programming Language :: Python :: 3
Classifier: License :: OSI Approved :: MIT License
Classifier: Operating System :: OS Independent
Requires-Python: >=3.9
License-File: LICENSE
Requires-Dist: redis
Provides-Extra: dev
Requires-Dist: redis ; extra == 'dev'
Provides-Extra: lint
Requires-Dist: pylint ; extra == 'lint'
Provides-Extra: test
Requires-Dist: flake8 ; extra == 'test'
Requires-Dist: pytest ; extra == 'test'
